jymkit/__init__.py
jymkit/py.typed
jymkit-0.0.20.dist-info/WHEEL
jymkit-0.0.20.dist-info/METADATA
jymkit-0.0.20.dist-info/RECORD
