Metadata-Version: 2.3
Name: jymkit
Version: 0.0.20
Summary: Jaxnasium
Author: Koen Ponse
Author-email: Koen Ponse <k.ponse@liacs.leidenuniv.nl>
Requires-Dist: jaxnasium
Requires-Python: >=3.11
